uht_tooling/__init__.py
uht_tooling/cli.py
uht_tooling/models/__init__.py
uht_tooling/workflows/__init__.py
uht_tooling/workflows/design_gibson.py
uht_tooling/workflows/design_slim.py
uht_tooling/workflows/gui.py
uht_tooling/workflows/mut_rate.py
uht_tooling/workflows/mutation_caller.py
uht_tooling/workflows/nextera_designer.py
uht_tooling/workflows/profile_inserts.py
uht_tooling/workflows/umi_hunter.py
uht_tooling-0.1.7.dist-info/METADATA
uht_tooling-0.1.7.dist-info/WHEEL
uht_tooling-0.1.7.dist-info/entry_points.txt
uht_tooling-0.1.7.dist-info/top_level.txt
uht_tooling-0.1.7.dist-info/RECORD
