Metadata-Version: 2.4
Name: uht-tooling
Version: 0.1.7
Summary: Tooling for ultra-high throughput screening workflows.
Author: Matt115A
License: MIT
Requires-Python: >=3.8
Requires-Dist: biopython==1.85
Requires-Dist: fuzzywuzzy==0.18.0
Requires-Dist: matplotlib==3.10.7
Requires-Dist: pandas==2.3.3
Requires-Dist: python-Levenshtein==0.27.3
Requires-Dist: pyyaml==6.0.3
Requires-Dist: pysam==0.23.3
Requires-Dist: scipy==1.15.3
Requires-Dist: seaborn==0.13.2
Requires-Dist: tabulate==0.9.0
Requires-Dist: tqdm==4.67.1
Requires-Dist: typer==0.20.0
Requires-Dist: mappy==2.30
Requires-Dist: gradio==5.49.1
Provides-Extra: gui
Requires-Dist: gradio==5.49.1; extra == "gui"
Provides-Extra: dev
Requires-Dist: pytest==9.0.0; extra == "dev"
Requires-Dist: black==25.9.0; extra == "dev"
Requires-Dist: ruff==0.14.4; extra == "dev"
